{"cameraMode":{"drawMode":0,"name":"Shaded","section":"Shading Mode"},"sceneLighting":true,"audioPlay":false,"sceneViewState":{"showFog":true,"showMaterialUpdate":false,"showSkybox":true,"showFlares":true,"showImageEffects":true,"showParticleSystems":true},"in2DMode":false,"pivot":{"x":8.61168384552002,"y":0.33773374557495119,"z":2.5832743644714357},"rotation":{"x":0.0706053152680397,"y":0.5139237642288208,"z":-0.042495716363191608,"w":0.8538684844970703},"size":13.863304138183594,"orthographic":false}